collective.recipe.supervisor-1.0.0-py3.6-nspkg.pth
collective/recipe/supervisor/__init__.py
collective/recipe/supervisor/recipe.rst
collective/recipe/supervisor/templates.py
collective/recipe/supervisor/tests/__init__.py
collective/recipe/supervisor/tests/test_docs.py
collective.recipe.supervisor-1.0.0.dist-info/METADATA
collective.recipe.supervisor-1.0.0.dist-info/WHEEL
collective.recipe.supervisor-1.0.0.dist-info/entry_points.txt
collective.recipe.supervisor-1.0.0.dist-info/namespace_packages.txt
collective.recipe.supervisor-1.0.0.dist-info/top_level.txt
collective.recipe.supervisor-1.0.0.dist-info/RECORD
