Metadata-Version: 2.1
Name: collective.recipe.supervisor
Version: 1.0.0
Summary: A buildout recipe to install supervisor
Home-page: https://github.com/collective/collective.recipe.supervisor/
Author: Mustapha Benali
Author-email: mustapha@headnet.dk
License: ZPL
Keywords: buildout recipe supervisor
Platform: UNKNOWN
Classifier: Development Status :: 6 - Mature
Classifier: Framework :: Buildout
Classifier: Intended Audience :: Developers
Classifier: License :: OSI Approved :: Zope Public License
Classifier: Programming Language :: Python
Classifier: Programming Language :: Python :: 2
Classifier: Programming Language :: Python :: 2.7
Classifier: Programming Language :: Python :: 3
Classifier: Programming Language :: Python :: 3.6
Classifier: Programming Language :: Python :: 3.7
Classifier: Topic :: Software Development :: Build Tools
Classifier: Topic :: Software Development :: Libraries :: Python Modules
Requires-Dist: setuptools
Requires-Dist: zc.buildout
Requires-Dist: zc.recipe.egg
Provides-Extra: test
Requires-Dist: zc.buildout[test] ; extra == 'test'
